darklens/__cli__.py
darklens/__init__.py
darklens/_version.py
darklens/conf/about/darklens.yaml
darklens/py.typed
dark_lens-0.1.0.dist-info/LICENSE
dark_lens-0.1.0.dist-info/METADATA
dark_lens-0.1.0.dist-info/WHEEL
dark_lens-0.1.0.dist-info/entry_points.txt
dark_lens-0.1.0.dist-info/RECORD
