Metadata-Version: 2.1
Name: dark-lens
Version: 0.1.0
Summary: AI-driven dark tourism guide and content creator for Jeju Island, offering personalized historical insights and immersive experiences.
Home-page: https://darklens.jeju.ai
License: Apache-2.0
Author: Dark Lens Team
Author-email: entelecheia@hotmail.com
Requires-Python: >=3.9,<3.13
Classifier: License :: OSI Approved :: Apache Software License
Classifier: Programming Language :: Python :: 3
Classifier: Programming Language :: Python :: 3.9
Classifier: Programming Language :: Python :: 3.10
Classifier: Programming Language :: Python :: 3.11
Classifier: Programming Language :: Python :: 3.12
Requires-Dist: click (>=8.1.3,<9.0.0)
Project-URL: Repository, https://github.com/jeju-ai/dark-lens
